{
	"name": "Parquet1",
	"properties": {
		"linkedServiceName": {
			"referenceName": "ADLS_Link",
			"type": "LinkedServiceReference"
		},
		"annotations": [],
		"type": "Parquet",
		"typeProperties": {
			"location": {
				"type": "AzureBlobFSLocation",
				"folderPath": "SalesLT",
				"fileSystem": "gold"
			},
			"compressionCodec": "snappy"
		},
		"schema": [
			{
				"name": "Address_ID",
				"type": "INT_32"
			},
			{
				"name": "Address_Line1",
				"type": "UTF8"
			},
			{
				"name": "Address_Line2",
				"type": "UTF8"
			},
			{
				"name": "City",
				"type": "UTF8"
			},
			{
				"name": "State_Province",
				"type": "UTF8"
			},
			{
				"name": "Country_Region",
				"type": "UTF8"
			},
			{
				"name": "Postal_Code",
				"type": "UTF8"
			},
			{
				"name": "rowguid",
				"type": "UTF8"
			},
			{
				"name": "Modified_Date",
				"type": "UTF8"
			}
		]
	},
	"type": "Microsoft.DataFactory/factories/datasets"
}